{
  "eventsShort": [
    {
      "guid": "d0058e00-b114-4d1a-8c6a-7d6bfe4e853d",
      "softId": "DO",
      "title": "Новое событие",
      "type": "Рабочее совещание",
      "start": "2023-04-10T07:59:00",
      "end": "2023-04-10T08:59:00",
      "org": "ООО \"АПХ \"ЗЕЛЕНАЯ ДОЛИНА\"",
      "subdiv": "",
      "className": "Переговорная Помещение ДИТ (виртуальное)"
    },
    {
      "guid": "d6fcb79f-f8e8-4842-ae0e-8eb66437f096",
      "softId": "DO",
      "title": "Наименование события",
      "type": "Рабочее совещание",
      "start": "2023-05-10T16:11:00",
      "end": "2023-05-10T17:11:00",
      "org": "ООО \"АПХ \"ЗЕЛЕНАЯ ДОЛИНА\"",
      "subdiv": "14701000 г.Белгород, Администрация",
      "className": "Переговорная Помещение ДИТ (виртуальное)"
    },
    {
      "guid": "3a96a661-1796-4a2e-9f93-1c5457ac4724",
      "softId": "DO",
      "title": "Наименование события 2",
      "type": "Рабочее совещание",
      "start": "2023-05-24T16:14:00",
      "end": "2023-05-24T17:00:00",
      "org": "ООО \"АПХ \"ЗЕЛЕНАЯ ДОЛИНА\"",
      "subdiv": "14701000 г.Белгород, Администрация",
      "className": "Переговорная Помещение ДИТ (виртуальное)"
    }
  ]
}
